RSA
darabonba_rsa
