Metadata-Version: 2.1
Name: darabonba-rsa
Version: 0.0.7
Summary: 配合darabonba多语言兼容的RSA工具
Home-page: 
Author: ZhangMr
Author-email: 2864640437@qq.com
License: MIT
Classifier: License :: OSI Approved :: MIT License
Classifier: Programming Language :: Python
Classifier: Programming Language :: Python :: 3
Classifier: Programming Language :: Python :: 3.6
Classifier: Programming Language :: Python :: Implementation :: CPython
Classifier: Programming Language :: Python :: Implementation :: PyPy
Requires-Python: >=3.6.0
